README.md
setup.py
bitjoy/__init__.py
bitjoy.egg-info/PKG-INFO
bitjoy.egg-info/SOURCES.txt
bitjoy.egg-info/dependency_links.txt
bitjoy.egg-info/top_level.txt
bitjoy/dtypes/__init__.py
bitjoy/dtypes/bits.py
bitjoy/dtypes/bytes_.py
bitjoy/dtypes/circuits.py
bitjoy/dtypes/operators.py
bitjoy/utils/__init__.py
bitjoy/utils/functions.py