Metadata-Version: 2.1
Name: bitjoy
Version: 1.0
Summary: Bit, Bytes and Logical Gates Abstraction.
Home-page: https://github.com/senavs/BitJoy
Author: Matheus Sena Vasconcelos
Author-email: sena.matheus14@gmail.com
License: MIT
Keywords: bitjoy,bit,bytes,logical-operators,int_to_bytes,half-adder,full-adder,boolean,gates,abstraction
Platform: UNKNOWN
Classifier: Programming Language :: Python :: 3
Classifier: License :: OSI Approved :: MIT License
Classifier: Operating System :: OS Independent
